skellyforge/__init__.py
skellyforge/__main__.py
skellyforge/headless_task_worker_test.py
skellyforge/postprocess_GUI.py
skellyforge/freemocap_utils/config.py
skellyforge/freemocap_utils/constants.py
skellyforge/freemocap_utils/postprocessing_widgets/led_widgets.py
skellyforge/freemocap_utils/postprocessing_widgets/parameter_tree_builder.py
skellyforge/freemocap_utils/postprocessing_widgets/parameter_widgets.py
skellyforge/freemocap_utils/postprocessing_widgets/stylesheet.py
skellyforge/freemocap_utils/postprocessing_widgets/task_worker_thread.py
skellyforge/freemocap_utils/postprocessing_widgets/menus/filtering_menu.py
skellyforge/freemocap_utils/postprocessing_widgets/menus/interpolation_menu.py
skellyforge/freemocap_utils/postprocessing_widgets/menus/main_menu.py
skellyforge/freemocap_utils/postprocessing_widgets/postprocessing_functions/filter_data.py
skellyforge/freemocap_utils/postprocessing_widgets/postprocessing_functions/good_frame_finder.py
skellyforge/freemocap_utils/postprocessing_widgets/postprocessing_functions/interpolate_data.py
skellyforge/freemocap_utils/postprocessing_widgets/postprocessing_functions/rotate_skeleton.py
skellyforge/freemocap_utils/postprocessing_widgets/visualization_widgets/marker_selector_widget.py
skellyforge/freemocap_utils/postprocessing_widgets/visualization_widgets/skeleton_builder.py
skellyforge/freemocap_utils/postprocessing_widgets/visualization_widgets/skeleton_view_widget.py
skellyforge/freemocap_utils/postprocessing_widgets/visualization_widgets/skeleton_viewers_container.py
skellyforge/freemocap_utils/postprocessing_widgets/visualization_widgets/slider_widget.py
skellyforge/freemocap_utils/postprocessing_widgets/visualization_widgets/timeseries_view_widget.py
skellyforge-2024.12.1009.dist-info/entry_points.txt
skellyforge-2024.12.1009.dist-info/LICENSE
skellyforge-2024.12.1009.dist-info/WHEEL
skellyforge-2024.12.1009.dist-info/METADATA
skellyforge-2024.12.1009.dist-info/RECORD
