Metadata-Version: 2.3
Name: skellyforge
Version: 2024.12.1009
Summary: Basic template of a python repository
Keywords: basic,template,python,repository
Author-email: skellyforge <info@freemocap.org>
Requires-Python: >=3.9,<3.13
Classifier: License :: OSI Approved :: GNU Affero General Public License v3 or later (AGPLv3+)
Classifier: Programming Language :: Python
Classifier: Programming Language :: Python :: 3
Requires-Dist: numpy==1.26.2
Requires-Dist: pyside6==6.6.*
Requires-Dist: pyqtgraph==0.13.3
Requires-Dist: scipy==1.11.4
Requires-Dist: rich==13.7.0
Requires-Dist: pandas==2.1.4
Requires-Dist: matplotlib==3.8.2
Requires-Dist: toml==0.10.2
Requires-Dist: black ; extra == "dev"
Requires-Dist: bumpver ; extra == "dev"
Requires-Dist: isort ; extra == "dev"
Requires-Dist: pip-tools ; extra == "dev"
Requires-Dist: pytest ; extra == "dev"
Provides-Extra: dev
